MANIFEST.in
README.rst
setup.cfg
setup.py
docs/HISTORY.txt
docs/INSTALL.txt
docs/LICENSE.GPL
docs/LICENSE.txt
plonetheme/__init__.py
plonetheme.fui.egg-info/PKG-INFO
plonetheme.fui.egg-info/SOURCES.txt
plonetheme.fui.egg-info/dependency_links.txt
plonetheme.fui.egg-info/entry_points.txt
plonetheme.fui.egg-info/namespace_packages.txt
plonetheme.fui.egg-info/not-zip-safe
plonetheme.fui.egg-info/paster_plugins.txt
plonetheme.fui.egg-info/requires.txt
plonetheme.fui.egg-info/top_level.txt
plonetheme/fui/__init__.py
plonetheme/fui/configure.zcml
plonetheme/fui/profiles.zcml
plonetheme/fui/setuphandlers.py
plonetheme/fui/skins.zcml
plonetheme/fui/tests.py
plonetheme/fui/version.txt
plonetheme/fui/browser/__init__.py
plonetheme/fui/browser/configure.zcml
plonetheme/fui/browser/interfaces.py
plonetheme/fui/browser/viewlet.pt
plonetheme/fui/browser/viewlets.py
plonetheme/fui/browser/images/README.txt
plonetheme/fui/browser/images/background.png
plonetheme/fui/browser/javascripts/prettify.js
plonetheme/fui/browser/stylesheets/README.txt
plonetheme/fui/browser/stylesheets/main.css
plonetheme/fui/browser/stylesheets/prettify.css
plonetheme/fui/profiles/default/cssregistry.xml
plonetheme/fui/profiles/default/import_steps.xml
plonetheme/fui/profiles/default/jsregistry.xml
plonetheme/fui/profiles/default/metadata.xml
plonetheme/fui/profiles/default/plonetheme.fui_various.txt
plonetheme/fui/profiles/default/skins.xml
plonetheme/fui/profiles/default/viewlets.xml
plonetheme/fui/skins/plonetheme_fui_custom_images/CONTENT.txt
plonetheme/fui/skins/plonetheme_fui_custom_templates/CONTENT.txt
plonetheme/fui/skins/plonetheme_fui_styles/CONTENT.txt
plonetheme/fui/skins/plonetheme_fui_styles/base.css.dtml
plonetheme/fui/skins/plonetheme_fui_styles/base_properties.props
plonetheme/fui/skins/plonetheme_fui_styles/portlets.css.dtml
plonetheme/fui/skins/plonetheme_fui_styles/public.css.dtml