Metadata-Version: 1.0
Name: plonetheme.fui
Version: 2.1.8
Summary: A Plone 3.0 theme for FUI
Home-page: http://github.com/espenak/plonetheme.fui
Author: Espen A. Kristiansen
Author-email: post@espenak.net
License: GPL
Keywords: web zope plone theme
Platform: UNKNOWN
Classifier: Framework :: Plone
Classifier: Programming Language :: Python
Classifier: Topic :: Software Development :: Libraries :: Python Modules
